{"id": "parallel_9", "result": "find_movie_showing(location=\"San Diego, CA\", movie=[\"Tenet\", \"No Time To Die\"], time=[\"5 pm\", \"7:30 pm\"])", "input_token_count": 327, "output_token_count": 34, "latency": 2.7836971282958984}
{"id": "parallel_23", "result": "alimony_calculator.ca.calculate(payor_income=10000, recipient_income=3000, duration=10), alimony_calculator.ca.calculate(payor_income=10000, recipient_income=3000, duration=20)", "input_token_count": 381, "output_token_count": 49, "latency": 3.1397287845611572}
{"id": "parallel_36", "result": "[paint_color_mixture(paint_type='Watercolor', color='Magenta'), paint_color_mixture(paint_type='Acrylic', color='Navy')]", "input_token_count": 352, "output_token_count": 34, "latency": 2.66156005859375}
{"id": "parallel_44", "result": "concert.find_nearby(location=\"Berlin\", date=\"next Friday\", genre=\"classical\", amenities=['Parking']), concert.find_nearby(location=\"Paris\", date=\"next Friday\", genre=\"classical\", amenities=['Parking'])", "input_token_count": 353, "output_token_count": 45, "latency": 2.999046802520752}
{"id": "parallel_56", "result": "hotel_booking.check_availability(hotel_name='Queens Hotel', location='Berlin, Germany', check_in_date='2022-03-10', check_out_date='2022-03-20'), hotel_booking.check_availability(hotel_name='Royal Hotel', location='Paris, France', check_in_date='2022-04-05', check_out_date='2022-04-15')", "input_token_count": 379, "output_token_count": 82, "latency": 4.081115484237671}
{"id": "parallel_61", "result": "math.hypot(x=3, y=4), math.hypot(x=6, y=8), math.hypot(x=9, y=12, z=15)", "input_token_count": 417, "output_token_count": 41, "latency": 2.823676109313965}
{"id": "parallel_77", "result": "math.hcf(number1=45, number2=60), math.hcf(number1=math.hcf(number1=45, number2=60), number2=math.hcf(number1=90, number2=120)), math.hcf(number1=36, number2=48), math.hcf(number1=math.hcf(number1=36, number2=48), number2=math.hcf(number1=72, number2=96))", "input_token_count": 354, "output_token_count": 97, "latency": 4.439773321151733}
{"id": "parallel_91", "result": "vegan_restaurant.find_nearby(location=\"Los Angeles, CA\", operating_hours=22), vegan_restaurant.find_nearby(location=\"San Francisco, CA\", operating_hours=22), vegan_restaurant.find_nearby(location=\"Seattle, WA\", operating_hours=22)", "input_token_count": 371, "output_token_count": 55, "latency": 3.2085049152374268}
{"id": "parallel_101", "result": "calculate_density(mass=10, volume=2, unit='kg/m\u00b3'), calculate_density(mass=15, volume=3, unit='kg/m\u00b3')", "input_token_count": 393, "output_token_count": 35, "latency": 2.589956521987915}
{"id": "parallel_103", "result": "entropy_change.calculate(substance=\"A\", mass=2, initial_temperature=25, final_temperature=75, pressure=1), entropy_change.calculate(substance=\"A\", mass=2, initial_temperature=10, final_temperature=50, pressure=1)", "input_token_count": 467, "output_token_count": 53, "latency": 3.157789468765259}
{"id": "parallel_108", "result": "[biology.get_cell_info(cell_type='neuron', detailed=True), biology.get_cell_info(cell_type='muscle', detailed=False)]", "input_token_count": 333, "output_token_count": 28, "latency": 2.344818353652954}
{"id": "parallel_121", "result": "ecology.get_turtle_population(location=\"Galapagos Islands\", year=2015, species=True), ecology.get_turtle_population(location=\"Galapagos Islands\", year=2020, species=True)", "input_token_count": 364, "output_token_count": 42, "latency": 2.7638463973999023}
{"id": "parallel_174", "result": "calculate_return_on_investment(purchase_price=150, sale_price=180, dividend=20), calculate_return_on_investment(purchase_price=200, sale_price=210, dividend=30), calculate_return_on_investment(purchase_price=250, sale_price=300, dividend=40)", "input_token_count": 405, "output_token_count": 61, "latency": 3.3311657905578613}
{"id": "parallel_184", "result": "algebra.quadratic_roots(a=3, b=7, c=2), algebra.quadratic_roots(a=5, b=-4, c=1)", "input_token_count": 427, "output_token_count": 36, "latency": 2.567415952682495}
{"id": "parallel_191", "result": "public_library.find_nearby(location=\"New York, NY\", facilities=[\"Reading Room\", \"Fiction\"]), public_library.find_nearby(location=\"Los Angeles, CA\", facilities=[\"Wi-Fi\", \"Children Section\"]), public_library.find_nearby(location=\"Chicago, IL\", facilities=[\"Cafe\", \"Reading Room\"])", "input_token_count": 351, "output_token_count": 63, "latency": 3.3851842880249023}
