{"id": "live_parallel_0-0-0", "result": "<TOOLCALL>[get_current_weather(location=\"\u5317\u4eac\"), get_current_weather(location=\"\u4e0a\u6d77\")]</TOOLCALL>", "input_token_count": 407, "output_token_count": 292, "latency": 6.857740163803101, "reasoning_content": "\u597d\u7684\uff0c\u7528\u6237\u95ee\u4e86\u5317\u4eac\u548c\u4e0a\u6d77\u7684\u5f53\u524d\u5929\u6c14\u72b6\u51b5\u3002\u6211\u9700\u8981\u4f7f\u7528\u63d0\u4f9b\u7684\u51fd\u6570get_current_weather\u6765\u83b7\u53d6\u8fd9\u4e24\u4e2a\u57ce\u5e02\u7684\u5929\u6c14\u4fe1\u606f\u3002\u9996\u5148\uff0c\u68c0\u67e5\u51fd\u6570\u7684\u53c2\u6570\uff0c\u53d1\u73b0\u9700\u8981location\u548c\u53ef\u9009\u7684unit\u3002\u7528\u6237\u6ca1\u6709\u6307\u5b9a\u5355\u4f4d\uff0c\u6240\u4ee5\u53ef\u80fd\u9ed8\u8ba4\u4f7f\u7528\u6444\u6c0f\u5ea6\u6216\u8005\u51fd\u6570\u7684\u9ed8\u8ba4\u8bbe\u7f6e\u3002\u63a5\u4e0b\u6765\uff0c\u786e\u4fddlocation\u53c2\u6570\u6b63\u786e\uff0c\u5317\u4eac\u548c\u4e0a\u6d77\u90fd\u662f\u4e2d\u56fd\u7684\u4e00\u7ebf\u57ce\u5e02\uff0c\u683c\u5f0f\u5e94\u8be5\u662f\u201c\u57ce\u5e02, \u7701\u201d\uff0c\u6bd4\u5982\u201c\u5317\u4eac, \u5317\u4eac\u201d\u6216\u8005\u201c\u4e0a\u6d77, \u4e0a\u6d77\u201d\u3002\u4e0d\u8fc7\u901a\u5e38\u53ef\u80fd\u76f4\u63a5\u5199\u201c\u5317\u4eac\u201d\u6216\u201c\u4e0a\u6d77\u201d\u5c31\u53ef\u4ee5\u4e86\uff0c\u4f46\u6839\u636e\u51fd\u6570\u63cf\u8ff0\u4e2d\u7684\u4f8b\u5b50\uff0c\u53ef\u80fd\u9700\u8981\u66f4\u5b8c\u6574\u7684\u683c\u5f0f\u3002\u6bd4\u5982\uff0c\u5982\u679c\u51fd\u6570\u8981\u6c42\u5fc5\u987b\u5199\u6210\u201c\u57ce\u5e02, \u7701\u201d\uff0c\u90a3\u4e48\u53ef\u80fd\u9700\u8981\u786e\u8ba4\u6b63\u786e\u7684\u683c\u5f0f\u3002\u4f46\u7528\u6237\u7684\u95ee\u9898\u91cc\u6ca1\u6709\u63d0\u5230\u7701\uff0c\u6240\u4ee5\u53ef\u80fd\u76f4\u63a5\u5199\u201c\u5317\u4eac\u201d\u548c\u201c\u4e0a\u6d77\u201d\u4f5c\u4e3alocation\u53c2\u6570\u7684\u503c\u3002\u7136\u540e\uff0c\u9700\u8981\u5206\u522b\u8c03\u7528\u4e24\u6b21\u51fd\u6570\uff0c\u4e00\u6b21\u83b7\u53d6\u5317\u4eac\u7684\u5929\u6c14\uff0c\u53e6\u4e00\u6b21\u83b7\u53d6\u4e0a\u6d77\u7684\u5929\u6c14\u3002\u56e0\u6b64\uff0c\u751f\u6210\u4e24\u4e2a\u51fd\u6570\u8c03\u7528\uff0c\u53c2\u6570\u5206\u522b\u4e3alocation=\"\u5317\u4eac\"\u548clocation=\"\u4e0a\u6d77\"\u3002\u5355\u4f4d\u53c2\u6570\u53ef\u4ee5\u7701\u7565\uff0c\u56e0\u4e3a\u662f\u53ef\u9009\u7684\uff0c\u6216\u8005\u7528\u6237\u53ef\u80fd\u5e0c\u671b\u4f7f\u7528\u9ed8\u8ba4\u5355\u4f4d\uff0c\u6bd4\u5982\u6444\u6c0f\u5ea6\u3002\u6240\u4ee5\u6700\u7ec8\u7684\u5de5\u5177\u8c03\u7528\u5e94\u8be5\u662f\u4e24\u4e2aget_current_weather\u51fd\u6570\uff0c\u5206\u522b\u4f20\u5165\u5bf9\u5e94\u7684location\u53c2\u6570\u3002"}
{"id": "live_parallel_1-0-1", "result": "<TOOLCALL>[get_current_weather(location=\"Boston, MA\"), get_current_weather(location=\"San Francisco, CA\")]</TOOLCALL>", "input_token_count": 413, "output_token_count": 234, "latency": 5.609082937240601, "reasoning_content": "Okay, the user is asking for the current weather conditions in Boston, MA and San Francisco. Let me check the available functions. There's a function called get_current_weather that takes a location parameter. The location needs to be in the format 'City, State' or 'City, Country'. Boston is given as MA, which is the state abbreviation. San Francisco isn't specified with a state, but I know it's in California, so I should format it as 'San Francisco, CA'. The unit parameter is optional, but the user didn't specify, so maybe I can leave it out or default to a common unit like Fahrenheit or Celsius. Since the user didn't mention, maybe it's best to omit it unless required. The function requires the location, so I'll make two separate calls for each city. Let me make sure the parameters are correctly formatted. Yes, Boston, MA is correct, and San Francisco, CA. So I'll call the function twice with each location."}
{"id": "live_parallel_2-0-2", "result": "<TOOLCALL>[get_current_weather(location=\"Boston, MA\"), get_current_weather(location=\"San Francisco, CA\")]</TOOLCALL>", "input_token_count": 415, "output_token_count": 144, "latency": 3.6589510440826416, "reasoning_content": "Okay, the user is asking about the weather in Boston and San Francisco. Let me check the available functions. There's the get_current_weather function which takes a location parameter. The location needs to be in 'City, State' format. Both cities are in the US, so I can use 'Boston, MA' and 'San Francisco, CA'. The unit is optional, but since the user didn't specify, I'll leave it out. I need to make two separate function calls for each city. Let me structure the tool calls properly."}
{"id": "live_parallel_3-0-3", "result": "<TOOLCALL>[get_current_weather(location=\"Canc\u00fan, QR\"), get_current_weather(location=\"Playa del Carmen, QR\"), get_current_weather(location=\"Tulum, QR\")]</TOOLCALL>", "input_token_count": 470, "output_token_count": 364, "latency": 8.352487325668335, "reasoning_content": "Okay, the user is asking for the current weather conditions in three different locations: Canc\u00fan, QR; Playa del Carmen, QR; and Tulum, QR. First, I need to check if the function get_current_weather can handle these requests. The function requires a location parameter in the format 'City, State' or 'City, Country'. The user provided 'QR' which I assume is the state abbreviation for Quintana Roo, Mexico. That's correct since QR is the ISO code for Quintana Roo.\n\nEach location is in the same state, so I need to make three separate function calls for each city. The function allows specifying the unit, but the user didn't mention it, so I can omit that parameter. I'll structure each call with the location as specified. Let me verify the city names: Canc\u00fan, Playa del Carmen, and Tulum are all major cities in Quintana Roo. \n\nWait, the user wrote 'Playa del Carmen, QR' but the correct format would be 'Playa del Carmen, QR' since QR is the state. The function's description says to use the short form if using the state name, so QR is appropriate. Each city is correctly paired with the state. \n\nI need to make sure each function call is correctly formatted. The parameters should be location for each city and state. Since the unit is optional and not provided, I'll leave it out. So the three function calls will be get_current_weather with locations set to each city and QR. That should cover all the requested locations."}
{"id": "live_parallel_4-1-0", "result": "<TOOLCALL>[get_current_weather(location=\"Boston, USA\"), get_current_weather(location=\"San Francisco, USA\")]</TOOLCALL>", "input_token_count": 414, "output_token_count": 173, "latency": 4.318705320358276, "reasoning_content": "Okay, the user is asking for the current weather in Boston, USA and San Francisco, USA. Let me check the available functions. There's the get_current_weather function which requires a location parameter in 'City, Country' format. The URL parameter is optional.\n\nFirst, I need to call the function for Boston. The location would be \"Boston, USA\". Then, another call for San Francisco with \"San Francisco, USA\". Since the URL is optional, I can omit it unless provided. The user hasn't given specific URLs, so I'll just use the location parameters. Make sure the city names are correctly spelled and formatted. I'll generate two separate function calls for each city."}
{"id": "live_parallel_5-2-0", "result": "<TOOLCALL>[get_current_weather(location=\"Boston, MA\"), get_current_weather(location=\"San Francisco, CA\")]</TOOLCALL>", "input_token_count": 446, "output_token_count": 141, "latency": 3.40998911857605, "reasoning_content": "Okay, the user is asking for the current temperature in Boston, MA and San Francisco. Let me check the available functions. There's the get_current_weather function. It requires the location parameter in 'City, State' format. The user provided both locations correctly. The unit is optional, but since they didn't specify, I'll use the default. The URL has a default value, so I don't need to include it. I need to make two separate function calls for each city. Let me structure the tool calls accordingly."}
{"id": "live_parallel_6-3-0", "result": "<TOOLCALL>[get_snow_report(location=\"Paris, France\"), get_snow_report(location=\"Bordeaux, France\")]</TOOLCALL>", "input_token_count": 544, "output_token_count": 186, "latency": 4.63527250289917, "reasoning_content": "Okay, the user is asking about the snow conditions in Paris and Bordeaux. Let me see which functions I have available. There's get_snow_report, which is exactly for this purpose. The function requires a location parameter in the format 'City, Country' or 'City, State'. Since both Paris and Bordeaux are in France, I should format them as 'Paris, France' and 'Bordeaux, France'. The unit is optional, but the user didn't specify, so maybe I can leave it out or default to Celsius. I need to make two separate function calls for each city. Let me check if there are any other parameters needed. No, just location and unit. Alright, I'll structure the tool calls accordingly."}
{"id": "live_parallel_7-3-1", "result": "<TOOLCALL>[get_current_weather(location=\"Boston, MA\"), get_current_weather(location=\"San Francisco, CA\")]</TOOLCALL>", "input_token_count": 523, "output_token_count": 125, "latency": 3.007856607437134, "reasoning_content": "Okay, the user is asking about the weather in Boston and San Francisco. Let me check the available functions. There's get_current_weather which takes a location and unit. Since they didn't specify the unit, I can call it without that parameter. I need to make two separate calls, one for each city. The location format should be 'City, State', so Boston, MA and San Francisco, CA. I'll structure the tool calls accordingly."}
{"id": "live_parallel_8-4-0", "result": "<TOOLCALL>[todo(type=\"add\", content=\"Machine Learning Study Session\"), todo(type=\"delete\", content=\"todo random\")]</TOOLCALL>", "input_token_count": 407, "output_token_count": 327, "latency": 7.487716913223267, "reasoning_content": "Okay, let's see. The user wants to manage their tasks. They need to add a new task called 'Machine Learning Study Session' and delete a completed task named 'todo random'.\n\nFirst, I'll check the available functions. There's the 'todo' function which handles add, delete, or update actions. The parameters required are 'type' (the action) and 'content' (the task details).\n\nFor adding the new task, the type should be 'add' and the content is 'Machine Learning Study Session'. That's straightforward.\n\nNext, deleting the task 'todo random'. The type here should be 'delete' and the content is 'todo random'. I need to make sure that the function allows deletion by specifying the task name in the content. Assuming that's how it works, since the description says content is the details relevant to the action.\n\nWait, does the 'delete' action require the content to be the exact task name? The user mentioned the task is named 'todo random', so using that in content should work. The function's parameters don't specify needing an ID or anything else, just the content. So it's safe to proceed.\n\nI need to make two separate function calls: one for add and one for delete. Each with their respective content. The user might have more tasks, but in this case, they specified exactly two actions. So I'll generate both function calls in the required format."}
{"id": "live_parallel_9-5-0", "result": "<TOOLCALL>[get_aws_pricing(memory=2, cpu='single'), get_aws_pricing(memory=4, cpu='single')]</TOOLCALL>", "input_token_count": 502, "output_token_count": 357, "latency": 8.441716432571411, "reasoning_content": "Okay, let's see. The user is asking about the cost of AWS EC2 instances with 2GB and 4GB RAM and one CPU. First, I need to figure out which parameters to use for the get_aws_pricing function. The function requires memory (in GB) and CPU (as 'single', 'dual', or 'quad'). The user mentioned \"one CPU\", so the CPU parameter should be 'single'. \n\nFor the memory, they want 2GB and 4GB. So I need to make two separate function calls: one with memory=2 and another with memory=4. The other parameters like region and operating system are optional, but the user didn't specify them. The function allows those to be optional, so I can omit them. \n\nWait, the function's parameters are memory (integer, required), cpu (string, required), region (optional), and operating_system (optional). Since the user didn't mention region or OS, I can leave those out. So each call will have memory and cpu specified.\n\nSo first call: get_aws_pricing(memory=2, cpu='single'). Second call: get_aws_pricing(memory=4, cpu='single'). That should retrieve the pricing for both configurations. I need to make sure the CPU is correctly set to 'single' for both. The user is asking for two different machines, so two separate function calls are needed here. There's no way to get both in one call since the parameters differ. Alright, that's all I need."}
{"id": "live_parallel_10-6-0", "result": "<TOOLCALL>[hotel_booking_book(hotel_name=\"Sheraton Hotel\", location=\"New York, NY\", check_in=\"2022-05-01\", check_out=\"2022-05-05\", adults=2, children=1), hotel_booking_book(hotel_name=\"Marriott\", location=\"Los Angeles, CA\", check_in=\"2022-06-01\", check_out=\"2022-06-10\", adults=1, children=2)]</TOOLCALL>", "input_token_count": 641, "output_token_count": 428, "latency": 10.14090609550476, "reasoning_content": "Okay, let's see. The user wants to make two hotel reservations. First, I need to check the available functions. There's the hotel_booking_book function. Let me look at the parameters required. The function needs hotel_name, location, check_in, check_out, adults, and children. \n\nFor the first reservation: Sheraton Hotel in New York. The check-in is May 1, 2022, which should be formatted as YYYY-MM-DD, so 2022-05-01. Check-out is May 5, 2022, so 2022-05-05. Adults are 2, children 1. The location should be \"New York, NY\". That's all the required parameters.\n\nSecond reservation: Marriott in Los Angeles. Check-in June 1, 2022 (2022-06-01), check-out June 10, 2022 (2022-06-10). Adults 1, children 2. Location \"Los Angeles, CA\". \n\nI need to make sure all parameters are correctly formatted. The dates are in the right format, and the location includes the state abbreviation. Both function calls should be separate. Since the user mentioned \"a couple of hotel reservations,\" I need to call the function twice with each set of parameters. No parameters are missing here. So I can proceed to make both function calls."}
{"id": "live_parallel_11-7-0", "result": "<TOOLCALL>[log_food(food_name='frozen mango', portion_amount=8, portion_unit='pieces'), log_food(food_name='chai tea', portion_amount=1, portion_unit='cup'), log_food(food_name='pepperoni pizza', portion_amount=2, portion_unit='slice'), log_food(food_name='coffee', portion_amount=1, portion_unit='cup')]</TOOLCALL>", "input_token_count": 545, "output_token_count": 351, "latency": 8.050146579742432, "reasoning_content": "Okay, let's see. The user wants to log their food intake. They mentioned two instances: first, 8 pieces of frozen mango and a chai tea. Earlier, they had two slices of pepperoni pizza and a coffee.\n\nI need to use the log_food function for each item. The function requires food_name, portion_amount, portion_unit, and optionally meal_type and log_date. Since the user didn't specify meal types or dates, I'll omit those. \n\nFirst item: frozen mango. Portion amount is 8, unit is 'pieces'. So log_food(food_name='frozen mango', portion_amount=8, portion_unit='pieces').\n\nSecond item: chai tea. Assuming a standard portion, maybe 1 cup. So portion_amount=1, unit='cup'.\n\nThird item: pepperoni pizza slices. They had two slices, so portion_amount=2, unit='slice'.\n\nFourth item: coffee. Again, assuming 1 cup unless specified otherwise. So portion_amount=1, unit='cup'.\n\nNeed to make sure each item is logged separately. The user didn't mention dates, so I'll leave log_date out. Meal types like snack or meal could be inferred, but since it's not provided, better to skip. So four function calls in total."}
{"id": "live_parallel_12-8-0", "result": "<TOOLCALL>[log_food(food_name=\"iced coffee\", portion_amount=12.0, portion_unit=\"ounces\", meal_name=\"breakfast\"), log_food(food_name=\"banana\", portion_amount=1.0, portion_unit=\"pieces\", meal_name=\"breakfast\"), log_food(food_name=\"quesadilla\", portion_amount=1.0, portion_unit=\"pieces\", meal_name=\"lunch\"), log_food(food_name=\"asparagus\", portion_amount=4.0, portion_unit=\"ounces\", meal_name=\"breakfast\"), log_food(food_name=\"eggs\", portion_amount=2.0, portion_unit=\"pieces\", meal_name=\"breakfast\"), log_food(food_name=\"gluten free bread\", portion_amount=1.0, portion_unit=\"pieces\", meal_name=\"breakfast\")]</TOOLCALL>", "input_token_count": 520, "output_token_count": 539, "latency": 12.731458187103271, "reasoning_content": "Okay, let's see. The user wants to log their food intake for different meals. They provided three entries: breakfast with iced coffee and banana, lunch with a quesadilla, and another breakfast entry with asparagus, eggs, and gluten-free bread.\n\nFirst, I need to check the available function, which is log_food. The parameters required are food_name, portion_amount, portion_unit (optional), and meal_name. Each food item needs to be logged separately. \n\nFor the first breakfast entry: 12 oz iced coffee and a banana. The coffee has a portion amount of 12 ounces, and the meal is breakfast. The banana is one piece, so portion_amount is 1, unit is pieces. \n\nThen lunch: a quesadilla. Assuming one piece, so portion_amount 1, unit pieces, meal lunch.\n\nSecond breakfast entry: four ounces asparagus (portion 4, unit ounces), two eggs (portion 2, unit pieces), and one gluten-free bread (portion 1, pieces). All under breakfast.\n\nI need to make separate function calls for each food item. Check if all required parameters are present. Each has food_name, portion_amount, and meal_name. Portion_unit is optional, but provided where applicable. \n\nSo, total function calls: iced coffee (breakfast), banana (breakfast), quesadilla (lunch), asparagus (breakfast), eggs (breakfast), bread (breakfast). That's six calls. \n\nWait, the user mentioned \"For breakfast I had...\" and then another \"Breakfast...\" entry. Maybe they meant two separate breakfasts? Or a typo? But the function requires meal_name, so each entry is logged under the specified meal. So proceed as per the given meal names."}
{"id": "live_parallel_13-9-0", "result": "<TOOLCALL>[get_current_weather(location=\"Boston, MA\"), get_current_weather(location=\"San Francisco, CA\")]</TOOLCALL>", "input_token_count": 404, "output_token_count": 244, "latency": 5.697595596313477, "reasoning_content": "Okay, the user is asking for the current weather in Boston, MA and San Francisco. Let me check the available functions. There's the get_current_weather function which requires a location and an optional unit. The user didn't specify the unit, so I can default to Celsius or Fahrenheit. Since the function allows for both, maybe I should just use the default, which is probably Celsius unless specified otherwise. But the function's description says the user can choose, so maybe I should call the function twice for each city. Wait, the user mentioned \"San Francisco\" without a state abbreviation. The function's param example uses 'San Francisco, CA', so I need to make sure to include the state abbreviation. The user didn't provide it, but maybe they meant CA? I'll assume San Francisco is in California. So I'll call get_current_weather for Boston, MA and San Francisco, CA. Since unit isn't required, I can omit it. So two function calls: one for each location. Let me structure the tool calls accordingly."}
{"id": "live_parallel_14-10-0", "result": "<TOOLCALL>[get_current_weather(location=\"Boston, MA\"), get_current_weather(location=\"San Francisco, CA\")]</TOOLCALL>", "input_token_count": 394, "output_token_count": 188, "latency": 4.671381235122681, "reasoning_content": "Okay, the user is asking about the weather in Boston and San Francisco. Let me check the available functions. There's the get_current_weather function which takes a location parameter. The location needs to be in 'City, State' format. Both cities are in Massachusetts and California respectively, so I should format them as 'Boston, MA' and 'San Francisco, CA'. The unit is optional, but the user didn't specify, so maybe default to 'imperial' or 'metric'. Since it's not required, I can omit it. So I need to call the function twice, once for each city. Let me make sure the parameters are correct. Yes, the required parameter is location. So the tool calls should be get_current_weather for each city."}
{"id": "live_parallel_15-11-0", "result": "<TOOLCALL>[cmd_controller.execute(command=\"dir C:\\\\\", unit=\"seconds\"), cmd_controller.execute(command=\"echo. > C:\\\\testing.txt\", unit=\"seconds\")]</TOOLCALL>", "input_token_count": 388, "output_token_count": 421, "latency": 9.585278034210205, "reasoning_content": "Okay, let's see. The user wants to list files in the C drive and create a file called testing.txt. Hmm, I need to figure out how to do that using the available functions. The only function provided is cmd_controller.execute, which runs Windows commands.\n\nFirst, listing files in the C drive. In Windows, the command to list files is 'dir', so I should use 'dir C:\\\\' to list the contents of the C drive. But wait, the user might want to see all files, maybe including hidden ones? The default 'dir' doesn't show hidden files, but the user didn't specify, so maybe just the basic command is enough.\n\nNext, creating a new file called testing.txt. In Windows, I can use the 'echo.' command to create an empty file. So 'echo. > C:\\\\testing.txt' should create the file. But wait, if the file already exists, this command will overwrite it. The user didn't mention overwriting, but since they want to create it, maybe that's acceptable.\n\nI need to make sure the paths are correct. Using double backslashes in the command to escape them, like 'C:\\\\' instead of 'C:\\'. Also, the function parameters require the command as a string. So each command should be passed as a separate function call.\n\nWait, the function has a 'unit' parameter, but it's not required. The user didn't mention anything about time units, so I can ignore that parameter.\n\nSo the steps are: first execute 'dir C:\\\\' to list the files, then execute 'echo. > C:\\\\testing.txt' to create the file. Each as separate function calls. Let me check if those commands are correct. Yes, 'dir' lists directory contents, and 'echo.' creates a file. Alright, that should work."}
