{"id": "live_multiple_2-1-0", "result": "```json\n[{\"function\":\"uber.ride\",\"parameters\":{\"loc\":\"2150 Shattuck Ave, Berkeley, CA\",\"type\":\"plus\",\"time\":10}}]\n```", "input_token_count": 666, "output_token_count": 40, "latency": 2.8891489505767822}
{"id": "live_multiple_3-2-0", "result": "```json\n[{\"function\":\"api.weather\",\"parameters\":{\"loc\":\"Ha Noi\"}}\n]\n```", "input_token_count": 559, "output_token_count": 23, "latency": 2.50742244720459}
{"id": "live_multiple_22-4-14", "result": "```json\n[{\"function\":\"HNA_WQA.search\",\"parameters\":{\"keyword\":\"\uc784\uc9c4\uc65c\ub780\",\"result_format\":\"text\",\"language\":\"EN\",\"max_results\":10}}\n]\n```", "input_token_count": 1509, "output_token_count": 46, "latency": 3.0040974617004395}
{"id": "live_multiple_26-6-1", "result": "Okay, let's find Shishir Patil's birthday. I'll use `recall_memory_search` to look for his birthday in our conversation history.\n\n```json\n[{\"function\":\"recall_memory_search\",\"parameters\":{\"query\":\"Shishir Patil's birthday\",\"request_heartbeat\":false}}]\n```", "input_token_count": 3164, "output_token_count": 71, "latency": 3.6994211673736572}
{"id": "live_multiple_44-17-0", "result": "```json\n[{\"function\":\"BankStatementOverView\", \"parameters\":{\"bank_name\":\"U.S. Bank\", \"account_number\":\"1-523-1713-5704\", \"account_type\":\"checking\", \"full_name\":\"SILVER BUSINESS CHECKING\", \"transaction_overview\":{\"total_deposits\":7132.76, \"total_withdrawals\":5927.40, \"start_date\":\"2019-10-01\", \"end_date\":\"2019-10-31\"}}}\n]\n```", "input_token_count": 2379, "output_token_count": 134, "latency": 4.418964624404907}
{"id": "live_multiple_50-20-0", "result": "```json\n[{\"function\":\"get_movies\",\"parameters\":{\"city\":\"Noida\"}}]\n```", "input_token_count": 1172, "output_token_count": 22, "latency": 2.5111138820648193}
{"id": "live_multiple_61-23-0", "result": "```json\n[{\"function\":\"get_movies\",\"parameters\":{\"city\":\"Noida\"}}]\n```", "input_token_count": 1249, "output_token_count": 22, "latency": 2.497689962387085}
{"id": "live_multiple_67-28-0", "result": "```json\n[{\"function\":\"add_postgres_server\",\"parameters\":{\"host\":\"http://plgah.ca\",\"database\":\"maindb\",\"username\":\"pascal\",\"password\":\"securepassword123\"}}]\n```", "input_token_count": 655, "output_token_count": 46, "latency": 3.0248613357543945}
{"id": "live_multiple_69-30-0", "result": "```json\n[{\"function\":\"add_postgres_server\",\"parameters\":{\"nickname\":\"PrimaryDB\",\"host\":\"db.example.com\",\"port\":5432,\"database\":\"inventory\",\"username\":\"admin\",\"password\":\"1234567890\"}}]\n```", "input_token_count": 1063, "output_token_count": 60, "latency": 3.5344393253326416}
{"id": "live_multiple_79-36-0", "result": "```json\n[{\"function\":\"dartfx_help\",\"parameters\":{\"topic\":\"installation\"}}]\n```", "input_token_count": 1011, "output_token_count": 22, "latency": 2.5059545040130615}
{"id": "live_multiple_81-36-2", "result": "```json\n[{\"function\":\"add_mtnards_server\",\"parameters\":{\"host\":\"http://plga.ca\",\"api_key\":\"1234324\"}}]```", "input_token_count": 1007, "output_token_count": 41, "latency": 2.907888412475586}
{"id": "live_multiple_101-42-5", "result": "```json\n[{\"function\":\"connect_to_server\",\"parameters\":{\"nickname\":\"SQL01\",\"timeout\":60,\"retry_attempts\":3,\"use_ssl\":true}}]\n```", "input_token_count": 1955, "output_token_count": 41, "latency": 2.905142307281494}
{"id": "live_multiple_109-43-7", "result": "```json\n[{\"function\":\"list_servers\",\"parameters\":{\"type\":\"mtna\"}}]\n```", "input_token_count": 1979, "output_token_count": 22, "latency": 2.50941801071167}
{"id": "live_multiple_125-47-1", "result": "```json\n[{\"function\":\"add\",\"parameters\":{\"a\":10,\"b\":10}},{\"function\":\"add\",\"parameters\":{\"a\":10,\"b\":10}},{\"function\":\"add\",\"parameters\":{\"a\":10,\"b\":10}},{\"function\":\"add\",\"parameters\":{\"a\":10,\"b\":10}}]\n```", "input_token_count": 1789, "output_token_count": 75, "latency": 3.7929604053497314}
{"id": "live_multiple_129-50-1", "result": "```json\n[{\"function\":\"search_engine.query\",\"parameters\":{\"prompt\":\"the current prime minister of India\",\"include_after_year\":true}}]\n```", "input_token_count": 1480, "output_token_count": 35, "latency": 2.786269426345825}
{"id": "live_multiple_162-63-1", "result": "```json\n[{\"function\":\"get_detail_adriel_project\",\"parameters\":{\"project_name\":\"e-commerce-web\"}}]\n```", "input_token_count": 1104, "output_token_count": 32, "latency": 2.725217819213867}
{"id": "live_multiple_207-91-1", "result": "```json\n[{\"function\":\"get_tech_stack\",\"parameters\":{\"employee_id\":\"Adriel\"}}]\n```", "input_token_count": 1519, "output_token_count": 26, "latency": 2.580491065979004}
{"id": "live_multiple_217-93-0", "result": "```json\n[{\"function\":\"Subdomain\",\"parameters\":{\"domain\":\"google.com\"}}]\n```", "input_token_count": 5139, "output_token_count": 22, "latency": 2.5406811237335205}
{"id": "live_multiple_244-108-0", "result": "```json\n[{\"function\":\"version_api.VersionApi.get_version\",\"parameters\":{}}]\n```", "input_token_count": 951, "output_token_count": 25, "latency": 2.578463315963745}
{"id": "live_multiple_256-120-0", "result": "```json\n[{\"function\":\"vex_api.VexApi.export_project_as_cyclone_dx1\",\"parameters\":{\"uuid\":\"123e4567-e89b-12d3-a456-426614174000\"}}]\n```", "input_token_count": 943, "output_token_count": 72, "latency": 3.7654781341552734}
{"id": "live_multiple_277-128-0", "result": "```json\n[{\"function\":\"Restaurants_2_FindRestaurants\",\"parameters\":{\"category\":\"American\",\"location\":\"New York, NY\",\"price_range\":\"moderate\",\"has_seating_outdoors\":true}}\n]\n```", "input_token_count": 1113, "output_token_count": 48, "latency": 3.117814540863037}
{"id": "live_multiple_305-131-4", "result": "```json\n[{\"function\":\"Hotels_4_SearchHotel\",\"parameters\":{\"location\":\"dontcare\",\"check_in_date\":\"2024-07-15\",\"stay_length\":5,\"number_of_rooms\":\"1\"}}]\n```", "input_token_count": 2027, "output_token_count": 57, "latency": 3.494969606399536}
{"id": "live_multiple_310-132-0", "result": "```json\n[{\"function\":\"Movies_3_FindMovies\",\"parameters\":{\"directed_by\":\"Herbert Ross\",\"genre\":\"Family\",\"cast\":\"Betsy Widhalm\"}}]\n```", "input_token_count": 1217, "output_token_count": 39, "latency": 2.885859251022339}
{"id": "live_multiple_337-133-1", "result": "```json\n[{\"function\":\"Music_3_PlayMedia\",\"parameters\":{\"track\":\"Remind Me\",\"artist\":\"Carrie Underwood\",\"device\":\"Living room\"}}\n]\n```", "input_token_count": 1081, "output_token_count": 37, "latency": 2.8474619388580322}
{"id": "live_multiple_348-133-12", "result": "```json\n[{\"function\":\"Music_3_LookupMusic\",\"parameters\":{\"artist\":\"Meghan Trainor\",\"year\":2018,\"genre\":\"Pop\",\"album\":\"dontcare\"}}]\n```", "input_token_count": 1065, "output_token_count": 43, "latency": 2.9625089168548584}
{"id": "live_multiple_367-134-12", "result": "```json\n[{\"function\":\"Movies_3_FindMovies\",\"parameters\":{\"directed_by\":\"dontcare\",\"genre\":\"Action\",\"cast\":\"dontcare\"}}]\n```", "input_token_count": 1056, "output_token_count": 36, "latency": 2.829490900039673}
{"id": "live_multiple_390-137-8", "result": "```json\n[{\"function\":\"Services_1_FindProvider\",\"parameters\":{\"city\":\"Pleasanton, CA\",\"is_unisex\":true}}]\n```", "input_token_count": 1088, "output_token_count": 34, "latency": 2.7608699798583984}
{"id": "live_multiple_409-140-5", "result": "```json\n[{\"function\":\"RideSharing_2_GetRide\",\"parameters\":{\"destination\":\"123 White Street, San Jose\",\"number_of_seats\":1,\"ride_type\":\"Pool\"}}]\n```", "input_token_count": 1036, "output_token_count": 46, "latency": 3.099111557006836}
{"id": "live_multiple_410-140-6", "result": "```json\n[{\"function\":\"RideSharing_2_GetRide\",\"parameters\":{\"destination\":\"3236 Grand Avenue, Oakland\",\"number_of_seats\":1,\"ride_type\":\"Luxury\"}}]\n```", "input_token_count": 1059, "output_token_count": 46, "latency": 3.0549185276031494}
{"id": "live_multiple_431-141-20", "result": "```json\n[{\"function\":\"Movies_1_GetTimesForMovie\",\"parameters\":{\"movie_name\":\"dontcare\",\"location\":\"Danville, CA\",\"show_date\":\"2024-01-27\",\"theater_name\":\"Century Blackhawk Plaza\",\"show_type\":\"imax\"}}]\n```", "input_token_count": 1147, "output_token_count": 66, "latency": 3.633542060852051}
{"id": "live_multiple_436-142-2", "result": "```json\n[{\"function\":\"RentalCars_3_GetCarsAvailable\",\"parameters\":{\"city\":\"Portland, OR\",\"start_date\":\"2023-04-22\",\"pickup_time\":\"10:00\",\"end_date\":\"2023-04-27\",\"car_type\":\"dontcare\"}}]\n```", "input_token_count": 2379, "output_token_count": 75, "latency": 3.820798397064209}
{"id": "live_multiple_445-144-5", "result": "```json\n[{\"function\":\"Services_4_FindProvider\",\"parameters\":{\"city\":\"Santa Rosa, CA\",\"type\":\"Psychologist\"}}]\n```", "input_token_count": 1663, "output_token_count": 32, "latency": 2.727102756500244}
{"id": "live_multiple_446-144-6", "result": "```json\n[{\"function\":\"Services_4_FindProvider\",\"parameters\":{\"city\":\"Vacaville, CA\",\"type\":\"Psychologist\"}}]\n```", "input_token_count": 1689, "output_token_count": 32, "latency": 2.723008394241333}
{"id": "live_multiple_451-145-2", "result": "```json\n[{\"function\":\"Flights_4_SearchRoundtripFlights\",\"parameters\":{\"origin_airport\":\"Atlanta, GA\",\"destination_airport\":\"Boston, MA\",\"departure_date\":\"2023-03-12\",\"return_date\":\"2023-03-19\",\"seating_class\":\"Economy\",\"number_of_tickets\":1}}]\n```", "input_token_count": 1955, "output_token_count": 82, "latency": 3.9117915630340576}
{"id": "live_multiple_460-145-11", "result": "```json\n[{\"function\":\"Hotels_2_SearchHouse\",\"parameters\":{\"where_to\":\"New York, NY\",\"has_laundry_service\":\"dontcare\",\"number_of_adults\":1,\"rating\":\"dontcare\"}},{\"function\":\"Travel_1_FindAttractions\",\"parameters\":{\"location\":\"New York, NY\",\"free_entry\":\"True\",\"category\":\"Park\",\"good_for_kids\":\"True\"}}]\n```", "input_token_count": 1913, "output_token_count": 93, "latency": 4.025420904159546}
{"id": "live_multiple_462-145-13", "result": "```json\n[{\"function\":\"Flights_4_SearchRoundtripFlights\",\"parameters\":{\"origin_airport\":\"San Francisco\",\"destination_airport\":\"Atlanta\",\"departure_date\":\"2023-03-01\",\"return_date\":\"2023-03-06\",\"seating_class\":\"Economy\",\"airlines\":\"American Airlines\"}}]\n```", "input_token_count": 1957, "output_token_count": 77, "latency": 3.8542320728302}
{"id": "live_multiple_466-145-17", "result": "```json\n[{\"function\":\"Travel_1_FindAttractions\",\"parameters\":{\"location\":\"New York, NY\",\"free_entry\":\"True\",\"category\":\"Shopping Area\",\"good_for_kids\":\"True\"}}]\n```", "input_token_count": 1911, "output_token_count": 47, "latency": 3.140817403793335}
{"id": "live_multiple_469-145-20", "result": "```json\n[{\"function\":\"Hotels_2_SearchHouse\",\"parameters\":{\"where_to\":\"Toronto, ON\",\"has_laundry_service\":\"dontcare\",\"number_of_adults\":1,\"rating\":\"dontcare\"}}]\n```", "input_token_count": 1925, "output_token_count": 53, "latency": 3.4110281467437744}
{"id": "live_multiple_484-146-9", "result": "```json\n[{\"function\":\"Music_3_LookupMusic\",\"parameters\":{\"artist\":\"dontcare\",\"album\":\"The New Classic\",\"genre\":\"dontcare\",\"year\":\"2017\"}}]\n```", "input_token_count": 852, "output_token_count": 43, "latency": 2.9987571239471436}
{"id": "live_multiple_489-147-4", "result": "```json\n[{\"function\":\"Trains_1_GetTrainTickets\",\"parameters\":{\"_from\":\"New York, NY\",\"to\":\"Phoenix, AZ\",\"date_of_journey\":\"04/23/2023\",\"journey_start_time\":\"13:45\",\"number_of_adults\":1,\"trip_protection\":false}}]\n```", "input_token_count": 2344, "output_token_count": 78, "latency": 3.8546831607818604}
{"id": "live_multiple_544-152-6", "result": "```json\n[{\"function\":\"Homes_2_FindHomeByArea\",\"parameters\":{\"area\":\"Mountain View, CA\",\"intent\":\"rent\",\"number_of_beds\":2,\"number_of_baths\":1,\"in_unit_laundry\":true}}\n]\n```", "input_token_count": 1061, "output_token_count": 60, "latency": 3.5352606773376465}
{"id": "live_multiple_545-152-7", "result": "```json\n[{\"function\":\"Homes_2_FindHomeByArea\",\"parameters\":{\"area\":\"Petaluma, CA\",\"intent\":\"rent\",\"number_of_beds\":2,\"number_of_baths\":2}}\n]\n```", "input_token_count": 1053, "output_token_count": 52, "latency": 3.3796770572662354}
{"id": "live_multiple_563-155-3", "result": "```json\n[{\"function\":\"Events_3_FindEvents\",\"parameters\":{\"event_type\":\"Music\",\"city\":\"Philadelphia, PA\",\"date\":\"2023-03-07\"}}]\n```", "input_token_count": 1891, "output_token_count": 45, "latency": 3.0702126026153564}
{"id": "live_multiple_568-155-8", "result": "```json\n[{\"function\":\"Events_3_FindEvents\",\"parameters\":{\"event_type\":\"Theater\",\"city\":\"New York, NY\",\"date\":\"2023-09-09\"}}]\n```", "input_token_count": 1890, "output_token_count": 46, "latency": 3.1004955768585205}
{"id": "live_multiple_569-155-9", "result": "```json\n[{\"function\":\"Events_3_FindEvents\",\"parameters\":{\"event_type\":\"Music, Theater\",\"city\":\"Las Vegas, NV\",\"date\":\"2023-03-06\"}}]\n```", "input_token_count": 1880, "output_token_count": 48, "latency": 3.157317638397217}
{"id": "live_multiple_585-157-6", "result": "```json\n[{\"function\":\"Media_3_FindMovies\",\"parameters\":{\"genre\":\"Action\",\"starring\":\"Bruce Willis\"}}]\n```", "input_token_count": 750, "output_token_count": 30, "latency": 2.6826446056365967}
{"id": "live_multiple_604-158-10", "result": "```json\n[{\"function\":\"Hotels_4_SearchHotel\",\"parameters\":{\"location\":\"Sacramento, CA\",\"star_rating\":\"dontcare\",\"smoking_allowed\":false,\"number_of_rooms\":\"dontcare\"}}]\n```", "input_token_count": 862, "output_token_count": 50, "latency": 3.3371036052703857}
{"id": "live_multiple_606-158-12", "result": "```json\n[{\"function\":\"Hotels_4_SearchHotel\",\"parameters\":{\"location\":\"Sydney, Australia\",\"star_rating\":\"4\",\"smoking_allowed\":true,\"number_of_rooms\":\"2\"}}]\n```", "input_token_count": 867, "output_token_count": 47, "latency": 3.1510345935821533}
{"id": "live_multiple_621-160-1", "result": "```json\n[{\"function\":\"Payment_1_MakePayment\",\"parameters\":{\"payment_method\":\"debit card\",\"amount\":154.0,\"receiver\":\"landlord's email\",\"private_visibility\":true}}\n]\n```", "input_token_count": 663, "output_token_count": 51, "latency": 3.364037275314331}
{"id": "live_multiple_625-160-5", "result": "```json\n[{\"function\":\"Payment_1_MakePayment\",\"parameters\":{\"payment_method\":\"debit card\",\"amount\":200.0,\"receiver\":\"amelia@example.com\",\"private_visibility\":true}}\n]\n```", "input_token_count": 672, "output_token_count": 52, "latency": 3.3892741203308105}
{"id": "live_multiple_639-161-7", "result": "```json\n[{\"function\":\"Music_3_LookupMusic\",\"parameters\":{\"artist\":\"dontcare\",\"album\":\"High Expectations\",\"genre\":\"dontcare\",\"year\":\"2019\"}}]\n```", "input_token_count": 1511, "output_token_count": 42, "latency": 2.97011661529541}
{"id": "live_multiple_646-161-14", "result": "```json\n[{\"function\":\"Music_3_LookupMusic\",\"parameters\":{\"artist\":\"dontcare\",\"album\":\"Starboy\",\"genre\":\"dontcare\",\"year\":\"2020\"}}]\n```", "input_token_count": 1505, "output_token_count": 42, "latency": 2.969754219055176}
{"id": "live_multiple_647-161-15", "result": "```json\n[{\"function\":\"Music_3_LookupMusic\",\"parameters\":{\"artist\":\"Ariana Grande\",\"album\":\"dontcare\",\"genre\":\"dontcare\",\"year\":\"2018\"}}]\n```", "input_token_count": 1498, "output_token_count": 43, "latency": 3.0090203285217285}
{"id": "live_multiple_649-161-17", "result": "```json\n[{\"function\":\"Music_3_LookupMusic\",\"parameters\":{\"artist\":\"dontcare\",\"album\":\"Narrated For You\",\"genre\":\"dontcare\",\"year\":\"2022\"}}]\n```", "input_token_count": 1502, "output_token_count": 44, "latency": 3.0490546226501465}
{"id": "live_multiple_660-162-2", "result": "```json\n[{\"function\":\"Events_3_FindEvents\",\"parameters\":{\"event_type\":\"Music,Theater\",\"city\":\"New York, NY\",\"date\":\"2024-03-10\"}}]\n```", "input_token_count": 2632, "output_token_count": 48, "latency": 3.162745714187622}
{"id": "live_multiple_667-162-9", "result": "```json\n[{\"function\":\"Events_3_FindEvents\",\"parameters\":{\"event_type\":\"Theater\",\"city\":\"New York, NY\",\"date\":\"2023-03-05\"}}]\n```", "input_token_count": 2637, "output_token_count": 46, "latency": 3.1026530265808105}
{"id": "live_multiple_681-163-6", "result": "```json\n[{\"function\":\"Weather_1_GetWeather\",\"parameters\":{\"city\":\"Vancouver, Canada\",\"date\":\"2023-03-10\"}}]\n```", "input_token_count": 992, "output_token_count": 39, "latency": 2.8826732635498047}
{"id": "live_multiple_702-164-18", "result": "```json\n[{\"function\":\"Movies_3_FindMovies\",\"parameters\":{\"cast\":\"Katsunosuke Hori\"}}\n]```", "input_token_count": 988, "output_token_count": 29, "latency": 2.656625270843506}
{"id": "live_multiple_709-164-25", "result": "```json\n[{\"function\":\"Movies_3_FindMovies\",\"parameters\":{\"directed_by\":\"Kirill Mikhanovsky\",\"genre\":\"Comedy-drama\"}}\n]```", "input_token_count": 996, "output_token_count": 36, "latency": 2.8170952796936035}
{"id": "live_multiple_718-165-5", "result": "```json\n[{\"function\":\"Hotels_2_BookHouse\",\"parameters\":{\"where_to\":\"Austin, TX\",\"number_of_adults\":4,\"check_in_date\":\"05/12/2023\",\"check_out_date\":\"05/18/2023\"}}]\n```", "input_token_count": 1175, "output_token_count": 72, "latency": 3.73935604095459}
{"id": "live_multiple_734-167-5", "result": "```json\n[{\"function\":\"Homes_2_FindHomeByArea\",\"parameters\":{\"type\":\"dict\",\"properties\":{\"area\":\"Los Angeles, CA\",\"intent\":\"buy\",\"number_of_beds\":2,\"number_of_baths\":2,\"has_garage\":true,\"in_unit_laundry\":\"dontcare\"}}}\n]\n```", "input_token_count": 1190, "output_token_count": 74, "latency": 3.774839401245117}
{"id": "live_multiple_759-169-14", "result": "```json\n[{\"function\":\"Media_3_FindMovies\",\"parameters\":{\"genre\":\"Comic\"}}]\n```", "input_token_count": 1539, "output_token_count": 24, "latency": 2.5667104721069336}
{"id": "live_multiple_799-175-5", "result": "```json\n[{\"function\":\"Weather_1_GetWeather\",\"parameters\":{\"city\":\"Lagunitas, CA\",\"date\":\"2023-04-15\"}}]\n```", "input_token_count": 1694, "output_token_count": 40, "latency": 2.9177446365356445}
{"id": "live_multiple_800-175-6", "result": "```json\n[{\"function\":\"Weather_1_GetWeather\",\"parameters\":{\"city\":\"San Pablo, CA\",\"date\":\"2023-04-10\"}}]\n```", "input_token_count": 1697, "output_token_count": 40, "latency": 2.921154260635376}
{"id": "live_multiple_808-175-14", "result": "```json\n[{\"function\":\"Weather_1_GetWeather\",\"parameters\":{\"city\":\"Antioch, CA\",\"date\":\"2023-10-04\"}}]\n```", "input_token_count": 1693, "output_token_count": 41, "latency": 2.9389729499816895}
{"id": "live_multiple_813-176-4", "result": "```json\n[{\"function\":\"Alarm_1_AddAlarm\",\"parameters\":{\"new_alarm_time\":\"16:30\",\"new_alarm_name\":\"Leave for home\"}}]\n```", "input_token_count": 586, "output_token_count": 42, "latency": 2.985501766204834}
{"id": "live_multiple_840-178-15", "result": "```json\n[{\"function\":\"Music_3_LookupMusic\",\"parameters\":{\"artist\":\"dontcare\",\"album\":\"Gotta Be Me\",\"genre\":\"dontcare\",\"year\":\"2019\"}}]\n```", "input_token_count": 1039, "output_token_count": 44, "latency": 3.053175926208496}
{"id": "live_multiple_847-179-1", "result": "```json\n[{\"function\":\"Restaurants_2_ReserveRestaurant\",\"parameters\":{\"restaurant_name\":\"Balthazar\",\"location\":\"New York, NY\",\"time\":\"20:00\",\"date\":\"2024-03-08\",\"number_of_seats\":4}}\n]\n```", "input_token_count": 950, "output_token_count": 65, "latency": 3.6063952445983887}
{"id": "live_multiple_855-180-3", "result": "```json\n[{\"function\":\"Buses_3_FindBus\",\"parameters\":{\"from_city\":\"Fresno, CA\",\"to_city\":\"Los Angeles, CA\",\"departure_date\":\"03/10/2023\",\"num_passengers\":1}}]\n```", "input_token_count": 1508, "output_token_count": 60, "latency": 3.5079572200775146}
{"id": "live_multiple_881-183-6", "result": "```json\n[{\"function\":\"Movies_1_FindAttractions\",\"parameters\":{\"location\":\"San Francisco, CA\",\"free_entry\":\"True\",\"category\":\"Park\",\"good_for_kids\":\"True\"}}]\n```", "input_token_count": 1863, "output_token_count": 46, "latency": 3.1313605308532715}
{"id": "live_multiple_893-185-3", "result": "```json\n[{\"function\":\"Payment_1_MakePayment\",\"parameters\":{\"payment_method\":\"debit card\",\"amount\":90.0,\"receiver\":\"Alice\",\"private_visibility\":false}}\n]\n```", "input_token_count": 1327, "output_token_count": 46, "latency": 3.1010165214538574}
{"id": "live_multiple_905-186-2", "result": "```json\n[{\"function\":\"Trains_1_GetTrainTickets\",\"parameters\":{\"_from\":\"Portland, OR\",\"to\":\"Seattle, WA\",\"date_of_journey\":\"2023-05-16\",\"journey_start_time\":\"08:00\",\"number_of_adults\":4,\"trip_protection\":true,\"_class\":\"Business\"}}]\n```", "input_token_count": 1493, "output_token_count": 83, "latency": 3.8745369911193848}
{"id": "live_multiple_911-190-0", "result": "```json\n[{\"function\":\"view_service_provider_profile\",\"parameters\":{\"service_id\":1}}\n]\n```", "input_token_count": 1156, "output_token_count": 28, "latency": 2.6440768241882324}
{"id": "live_multiple_934-191-22", "result": "```json\n[{\"function\":\"get_service_providers\",\"parameters\":{\"type\":\"dict\",\"province_id\":1,\"district_name\":\"Chatuchak\",\"start_available_date\":\"2024-03-22 00:00:00\",\"avg_rating\":1.0}}]\n```", "input_token_count": 1408, "output_token_count": 70, "latency": 3.7112648487091064}
{"id": "live_multiple_953-201-1", "result": "```json\n[{\"function\":\"flight.status.check\",\"parameters\":{\"flight_identifier\":\"IND5463\",\"passenger_name\":\"karan\",\"ticket_number\":\"IND5463\"}}]\n```", "input_token_count": 694, "output_token_count": 46, "latency": 3.1267504692077637}
{"id": "live_multiple_973-213-0", "result": "```json\n[{\"function\":\"get_service_providers\",\"parameters\":{\"province_id\":1,\"district_name\":\"All\",\"service_ids\":[2]}}\n]", "input_token_count": 1283, "output_token_count": 37, "latency": 2.8419861793518066}
{"id": "live_multiple_985-216-0", "result": "```json\n[{\"function\":\"reminders_complete\",\"parameters\":{\"token\":\"1231289312\"}}]\n```", "input_token_count": 5874, "output_token_count": 31, "latency": 2.7303171157836914}
{"id": "live_multiple_989-220-0", "result": "```json\n[{\"function\":\"get_websites\",\"parameters\":{\"status_filter\":\"active\"}}]\n```", "input_token_count": 666, "output_token_count": 23, "latency": 2.537940263748169}
{"id": "live_multiple_996-227-0", "result": "```json\n[{\"function\":\"add_service_config\",\"parameters\":{\"service_name\":\"fdsa\",\"configurations\":{\"timeout\":30,\"retry_count\":5,\"endpoint\":\"https://api.fdsa-service.com\",\"auth_required\":true}}}\n]```", "input_token_count": 924, "output_token_count": 58, "latency": 3.474661111831665}
{"id": "live_multiple_997-228-0", "result": "```json\n[{\"function\":\"usage_api.UsageApi.get_hosts_per_day\",\"parameters\":{\"day\":15,\"month\":2,\"year\":2022}}\n]\n```", "input_token_count": 829, "output_token_count": 45, "latency": 3.095729351043701}
{"id": "live_multiple_1002-232-1", "result": "```json\n[{\"function\":\"api_token_api.APITokenApi.get_api_tokens\",\"parameters\":{\"user_id\":\"user123\"}}]\n```", "input_token_count": 789, "output_token_count": 39, "latency": 2.880993604660034}
{"id": "live_multiple_1016-245-0", "result": "```json\n[{\"function\":\"create_global_application_alert_config\",\"parameters\":{\"name\":\"UrgentAlert77f7\",\"alert_type\":\"error_rate\",\"threshold\":0.05,\"recipients\":[\"admin@example.com\",\"support@example.com\"]}}]\n```", "input_token_count": 884, "output_token_count": 63, "latency": 3.5516414642333984}
{"id": "live_multiple_1017-246-0", "result": "```json\n[{\"function\":\"events_api.EventsApi.get_event\",\"parameters\":{\"eventId\":\"efJG9\"}}]\n```", "input_token_count": 533, "output_token_count": 30, "latency": 2.7119288444519043}
{"id": "live_multiple_1027-255-1", "result": "```json\n[{\"function\":\"api_token_api.APITokenApi.get_api_tokens\",\"parameters\":{\"user_id\":\"12345\"}}]\n```", "input_token_count": 845, "output_token_count": 40, "latency": 2.943368911743164}
{"id": "live_multiple_1040-267-0", "result": "```json\n[{\"function\":\"detail_experience_and_education\",\"parameters\":{\"experience_or_education_type\":\"Education at Universitas Sebelas Maret (UNS)\"}}\n]\n```", "input_token_count": 1527, "output_token_count": 42, "latency": 3.0138728618621826}
{"id": "live_multiple_1051-278-0", "result": "```json\n[{\"function\":\"set_alarm\",\"parameters\":{\"alarm_time\":\"2023-12-01 07:00:00\",\"purpose\":\"meeting\"}}]\n```", "input_token_count": 800, "output_token_count": 45, "latency": 3.109931230545044}
