{"id": "live_multiple_2-1-0", "result": "<TOOLCALL>uber.ride(loc=\"2150 Shattuck Ave, Berkeley, CA\", type=\"plus\", time=10)</TOOLCALL>", "input_token_count": 662, "output_token_count": 37, "latency": 4.942517042160034}
{"id": "live_multiple_3-2-0", "result": "<TOOLCALL>api.weather(loc=\"Ha Noi, Vietnam\")</TOOLCALL>", "input_token_count": 547, "output_token_count": 21, "latency": 2.89906907081604}
{"id": "live_multiple_22-4-14", "result": "<TOOLCALL>HNA_WQA.search(keyword=\"\uc784\uc9c4\uc65c\ub780\", result_format=\"text\", max_results=10)</TOOLCALL>", "input_token_count": 1497, "output_token_count": 32, "latency": 4.394364833831787}
{"id": "live_multiple_26-6-1", "result": "<TOOLCALL>[recall_memory_search(query=\"Shishir Patil birthday\", page=0, request_heartbeat=True)]</TOOLCALL>", "input_token_count": 3071, "output_token_count": 32, "latency": 4.660135269165039}
{"id": "live_multiple_44-17-0", "result": "<TOOLCALL>[BankStatementOverView(bank_name=\"U.S. Bank\", account_number=\"1-523-1713-5704\", account_type=\"checking\", full_name=\"SILVER BUSINESS CHECKING\", transaction_overview={\"total_deposits\": 7132.76, \"total_withdrawals\": 5927.4, \"start_date\": \"2019-10-01\", \"end_date\": \"2019-10-31\"}), transaction_summary.generate(transactions=[], starting_date=\"2019-10-01\", ending_date=\"2019-10-31\", total_deposits=7132.76, total_withdrawals=5927.4, starting_balance=5532.01, ending_balance=6737.37, firstname=\"\", lastname=\"\")]</TOOLCALL>", "input_token_count": 2318, "output_token_count": 209, "latency": 12.309120893478394}
{"id": "live_multiple_50-20-0", "result": "<TOOLCALL>[get_movies(city=\"Noida\", movie_date=\"04-11-2024\")]</TOOLCALL>", "input_token_count": 1177, "output_token_count": 33, "latency": 4.796283006668091}
{"id": "live_multiple_61-23-0", "result": "<TOOLCALL>get_movies(city=\"Noida\")</TOOLCALL>", "input_token_count": 1238, "output_token_count": 19, "latency": 3.1518192291259766}
{"id": "live_multiple_67-28-0", "result": "<TOOLCALL>add_postgres_server(host=\"http://plgah.ca\", port=5432, database=\"maindb\", username=\"pascal\", password=\"securepassword123\")</TOOLCALL>", "input_token_count": 641, "output_token_count": 49, "latency": 6.671916723251343}
{"id": "live_multiple_69-30-0", "result": "<TOOLCALL>add_postgres_server(nickname=\"PrimaryDB\", host=\"db.example.com\", port=5432, database=\"inventory\", username=\"admin\", password=\"1234567890\")</TOOLCALL>", "input_token_count": 1041, "output_token_count": 55, "latency": 7.056652545928955}
{"id": "live_multiple_79-36-0", "result": "<TOOLCALL>dartfx_help(topic=\"installation\")</TOOLCALL>", "input_token_count": 998, "output_token_count": 18, "latency": 3.141838550567627}
{"id": "live_multiple_81-36-2", "result": "<TOOLCALL>add_mtnards_server(host=\"http://plga.ca\", api_key=\"1234324\")</TOOLCALL>", "input_token_count": 995, "output_token_count": 35, "latency": 5.472491264343262}
{"id": "live_multiple_101-42-5", "result": "<TOOLCALL>connect_to_server(nickname=\"SQL01\", timeout=60)</TOOLCALL>", "input_token_count": 1915, "output_token_count": 25, "latency": 4.232102394104004}
{"id": "live_multiple_109-43-7", "result": "<TOOLCALL>list_servers(type=\"mtna\")</TOOLCALL>", "input_token_count": 1946, "output_token_count": 19, "latency": 3.4067840576171875}
{"id": "live_multiple_125-47-1", "result": "<TOOLCALL>multiply(a=3, b=10)</TOOLCALL>\n<TOOLCALL>add(a=\"multiply(a=3, b=10)\", b=0)</TOOLCALL>", "input_token_count": 1744, "output_token_count": 46, "latency": 6.642719030380249}
{"id": "live_multiple_129-50-1", "result": "<TOOLCALL>search_engine.query(prompt=\"the current prime minister of India\", include_after_year=True)</TOOLCALL>", "input_token_count": 1460, "output_token_count": 27, "latency": 4.762433052062988}
{"id": "live_multiple_162-63-1", "result": "<TOOLCALL>get_detail_adriel_project(project_name=\"e-commerce-web\", include_financials=False)</TOOLCALL>", "input_token_count": 1048, "output_token_count": 28, "latency": 4.894593238830566}
{"id": "live_multiple_207-91-1", "result": "<TOOLCALL>get_tech_stack(employee_id=\"Adriel\")</TOOLCALL>", "input_token_count": 1470, "output_token_count": 21, "latency": 4.085608005523682}
{"id": "live_multiple_217-93-0", "result": "<TOOLCALL>Subdomain(domain=\"google.com\")</TOOLCALL>", "input_token_count": 5066, "output_token_count": 18, "latency": 4.064297676086426}
{"id": "live_multiple_244-108-0", "result": "<TOOLCALL>version_api.VersionApi.get_version()</TOOLCALL>", "input_token_count": 914, "output_token_count": 17, "latency": 3.5245351791381836}
{"id": "live_multiple_256-120-0", "result": "<TOOLCALL>vex_api.VexApi.export_project_as_cyclone_dx1(uuid=\"123e4567-e89b-12d3-a456-426614174000\", download=False)</TOOLCALL>", "input_token_count": 918, "output_token_count": 63, "latency": 8.275406837463379}
{"id": "live_multiple_277-128-0", "result": "<TOOLCALL>Restaurants_2_FindRestaurants(category=\"American\", location=\"New York, NY\", price_range=\"moderate\", has_vegetarian_options=False, has_seating_outdoors=True)</TOOLCALL>", "input_token_count": 1102, "output_token_count": 48, "latency": 6.968137502670288}
{"id": "live_multiple_305-131-4", "result": "<TOOLCALL>Hotels_4_ReserveHotel(place_name=\"dontcare\", check_in_date=\"2023-07-15\", stay_length=5, location=\"Studio City, California\", number_of_rooms=\"1\")</TOOLCALL>", "input_token_count": 1998, "output_token_count": 57, "latency": 8.147270441055298}
{"id": "live_multiple_310-132-0", "result": "<TOOLCALL>Movies_3_FindMovies(directed_by=\"Herbert Ross\", genre=\"Family\", cast=\"Betsy Widhalm\")</TOOLCALL>", "input_token_count": 1211, "output_token_count": 36, "latency": 6.4340736865997314}
{"id": "live_multiple_337-133-1", "result": "<TOOLCALL>Music_3_PlayMedia(track=\"Remind Me\", artist=\"Carrie Underwood\", device=\"Living room\")</TOOLCALL>", "input_token_count": 1074, "output_token_count": 34, "latency": 6.243417978286743}
{"id": "live_multiple_348-133-12", "result": "<TOOLCALL>Music_3_LookupMusic(artist=\"Meghan Trainor\", album=\"dontcare\", genre=\"Pop\", year=2018)</TOOLCALL>", "input_token_count": 1057, "output_token_count": 40, "latency": 6.607515335083008}
{"id": "live_multiple_367-134-12", "result": "<TOOLCALL>Movies_3_FindMovies(directed_by=\"dontcare\", genre=\"Action\", cast=\"dontcare\")</TOOLCALL>", "input_token_count": 1050, "output_token_count": 32, "latency": 6.22927451133728}
{"id": "live_multiple_390-137-8", "result": "<TOOLCALL>Services_1_FindProvider(city=\"Pleasanton, CA\", is_unisex=True)</TOOLCALL>", "input_token_count": 1053, "output_token_count": 29, "latency": 5.988947629928589}
{"id": "live_multiple_409-140-5", "result": "<TOOLCALL>RideSharing_2_GetRide(destination=\"123 White Street, San Jose\", number_of_seats=1, ride_type=\"Pool\")</TOOLCALL>", "input_token_count": 1028, "output_token_count": 41, "latency": 6.804219007492065}
{"id": "live_multiple_410-140-6", "result": "<TOOLCALL>RideSharing_2_GetRide(destination=\"3236 Grand Avenue, Oakland\", number_of_seats=1, ride_type=\"Luxury\")</TOOLCALL>", "input_token_count": 1050, "output_token_count": 42, "latency": 6.982192039489746}
{"id": "live_multiple_431-141-20", "result": "<TOOLCALL>Movies_1_FindMovies(location=\"Danville, CA\", theater_name=\"Century Blackhawk Plaza\", show_type=\"imax\")</TOOLCALL>", "input_token_count": 1121, "output_token_count": 36, "latency": 6.519675254821777}
{"id": "live_multiple_436-142-2", "result": "<TOOLCALL>RentalCars_3_GetCarsAvailable(city=\"Portland, OR\", start_date=\"2023-04-22\", pickup_time=\"10:00\", end_date=\"2023-04-27\")</TOOLCALL>", "input_token_count": 2332, "output_token_count": 61, "latency": 8.591724157333374}
{"id": "live_multiple_445-144-5", "result": "<TOOLCALL>Services_4_FindProvider(city=\"Santa Rosa, CA\", type=\"Psychiatrist\")</TOOLCALL>", "input_token_count": 1634, "output_token_count": 29, "latency": 6.245896100997925}
{"id": "live_multiple_446-144-6", "result": "<TOOLCALL>Services_4_FindProvider(city=\"Vacaville, CA\", type=\"Psychologist\")</TOOLCALL>", "input_token_count": 1660, "output_token_count": 29, "latency": 6.2101428508758545}
{"id": "live_multiple_451-145-2", "result": "<TOOLCALL>[Flights_4_SearchRoundtripFlights(origin_airport=\"Atlanta, GA\", destination_airport=\"Boston, MA\", departure_date=\"2023-03-12\", return_date=\"2023-03-19\")]</TOOLCALL>", "input_token_count": 1922, "output_token_count": 64, "latency": 8.851036548614502}
{"id": "live_multiple_460-145-11", "result": "<TOOLCALL>Travel_1_FindAttractions(location=\"New York, NY\", free_entry=\"True\", category=\"Park\", good_for_kids=\"True\")</TOOLCALL>", "input_token_count": 1882, "output_token_count": 40, "latency": 6.960435152053833}
{"id": "live_multiple_462-145-13", "result": "<TOOLCALL>[Flights_4_SearchRoundtripFlights(origin_airport=\"San Francisco\", destination_airport=\"Atlanta\", departure_date=\"2023-03-01\", return_date=\"2023-03-06\", seating_class=\"Economy\", airlines=\"American Airlines\", number_of_tickets=1)]</TOOLCALL>", "input_token_count": 1927, "output_token_count": 78, "latency": 9.483845472335815}
{"id": "live_multiple_466-145-17", "result": "<TOOLCALL>Travel_1_FindAttractions(location=\"New York, NY\", free_entry=\"True\", category=\"Shopping Area\", good_for_kids=\"True\")</TOOLCALL>", "input_token_count": 1880, "output_token_count": 41, "latency": 7.138107776641846}
{"id": "live_multiple_469-145-20", "result": "<TOOLCALL>Travel_1_FindAttractions(location=\"Toronto, ON\", category=\"Park\", good_for_kids=\"True\", free_entry=\"dontcare\")</TOOLCALL>", "input_token_count": 1891, "output_token_count": 40, "latency": 7.000304698944092}
{"id": "live_multiple_484-146-9", "result": "<TOOLCALL>Music_3_LookupMusic(artist=\"dontcare\", album=\"The New Classic\", genre=\"dontcare\", year=\"2017\")</TOOLCALL>", "input_token_count": 836, "output_token_count": 41, "latency": 7.26011061668396}
{"id": "live_multiple_489-147-4", "result": "<TOOLCALL>Trains_1_GetTrainTickets(_from=\"New York, NY\", to=\"Phoenix, AZ\", date_of_journey=\"04/23/2023\", journey_start_time=\"13:45\", number_of_adults=1, trip_protection=False)</TOOLCALL>", "input_token_count": 2293, "output_token_count": 70, "latency": 9.271650791168213}
{"id": "live_multiple_544-152-6", "result": "<TOOLCALL>Homes_2_FindHomeByArea(area=\"Mountain View, CA\", intent=\"rent\", number_of_beds=2, number_of_baths=1, in_unit_laundry=True)</TOOLCALL>", "input_token_count": 1023, "output_token_count": 48, "latency": 8.082031965255737}
{"id": "live_multiple_545-152-7", "result": "<TOOLCALL>Homes_2_FindHomeByArea(area=\"Petaluma, CA\", intent=\"rent\", number_of_beds=2, number_of_baths=2)</TOOLCALL>", "input_token_count": 1016, "output_token_count": 43, "latency": 7.380414247512817}
{"id": "live_multiple_563-155-3", "result": "<TOOLCALL>Events_3_FindEvents(event_type=\"Music\", city=\"Philadelphia, PA\", date=\"2023-03-07\")</TOOLCALL>", "input_token_count": 1830, "output_token_count": 40, "latency": 7.309088230133057}
{"id": "live_multiple_568-155-8", "result": "<TOOLCALL>Events_3_FindEvents(event_type=\"Theater\", city=\"New York City, NY\", date=\"2023-09-09\")</TOOLCALL>", "input_token_count": 1827, "output_token_count": 43, "latency": 7.672523498535156}
{"id": "live_multiple_569-155-9", "result": "<TOOLCALL>Events_3_FindEvents(event_type=\"Music\", city=\"Las Vegas, NV\", date=\"2023-03-06\")</TOOLCALL>\n<TOOLCALL>Events_3_FindEvents(event_type=\"Theater\", city=\"Las Vegas, NV\", date=\"2023-03-06\")</TOOLCALL>", "input_token_count": 1818, "output_token_count": 82, "latency": 9.65234375}
{"id": "live_multiple_585-157-6", "result": "<TOOLCALL>Media_3_FindMovies(genre=\"Action\", starring=\"Bruce Willis\")</TOOLCALL>", "input_token_count": 739, "output_token_count": 26, "latency": 6.303775072097778}
{"id": "live_multiple_604-158-10", "result": "<TOOLCALL>[Hotels_4_SearchHotel(location=\"Sacramento, CA\")]</TOOLCALL>", "input_token_count": 836, "output_token_count": 24, "latency": 6.167674779891968}
{"id": "live_multiple_606-158-12", "result": "<TOOLCALL>[Hotels_4_SearchHotel(location=\"Sydney, AU\", star_rating=\"4\", smoking_allowed=True, number_of_rooms=\"2\")]</TOOLCALL>", "input_token_count": 840, "output_token_count": 39, "latency": 7.298616647720337}
{"id": "live_multiple_621-160-1", "result": "<TOOLCALL>Payment_1_MakePayment(payment_method=\"debit card\", amount=15400, receiver=\"landlord's email\", private_visibility=True)</TOOLCALL>", "input_token_count": 642, "output_token_count": 41, "latency": 7.459862232208252}
{"id": "live_multiple_625-160-5", "result": "<TOOLCALL>Payment_1_MakePayment(payment_method=\"debit card\", amount=200, receiver=\"amelia@example.com\", private_visibility=True)</TOOLCALL>", "input_token_count": 649, "output_token_count": 39, "latency": 7.281847238540649}
{"id": "live_multiple_639-161-7", "result": "<TOOLCALL>Music_3_LookupMusic(artist=\"dontcare\", album=\"High Expectations\", genre=\"dontcare\", year=\"2019\")</TOOLCALL>", "input_token_count": 1491, "output_token_count": 41, "latency": 7.444809198379517}
{"id": "live_multiple_646-161-14", "result": "<TOOLCALL>Music_3_LookupMusic(artist=\"dontcare\", album=\"Starboy\", genre=\"dontcare\", year=\"2020\")</TOOLCALL>", "input_token_count": 1484, "output_token_count": 40, "latency": 7.336626768112183}
{"id": "live_multiple_647-161-15", "result": "<TOOLCALL>Music_3_LookupMusic(artist=\"Ariana Grande\", year=\"2018\")</TOOLCALL>", "input_token_count": 1478, "output_token_count": 32, "latency": 6.719020128250122}
{"id": "live_multiple_649-161-17", "result": "<TOOLCALL>Music_3_LookupMusic(artist=\"dontcare\", album=\"Narrated For You\", genre=\"dontcare\", year=\"2022\")</TOOLCALL>", "input_token_count": 1481, "output_token_count": 41, "latency": 7.453829526901245}
{"id": "live_multiple_660-162-2", "result": "<TOOLCALL>Events_3_FindEvents(event_type=\"Music\", city=\"New York, NY\", date=\"2023-03-10\"), Events_3_FindEvents(event_type=\"Theater\", city=\"New York, NY\", date=\"2023-03-10\")</TOOLCALL>", "input_token_count": 2578, "output_token_count": 72, "latency": 9.415922164916992}
{"id": "live_multiple_667-162-9", "result": "<TOOLCALL>Events_3_FindEvents(event_type=\"Theater\", city=\"New York, NY\", date=\"2023-03-05\")</TOOLCALL>", "input_token_count": 2583, "output_token_count": 42, "latency": 7.714791536331177}
{"id": "live_multiple_681-163-6", "result": "<TOOLCALL>[Weather_1_GetWeather(city=\"Vancouver, Canada\", date=\"2023-03-10\")]</TOOLCALL>", "input_token_count": 980, "output_token_count": 36, "latency": 7.202865123748779}
{"id": "live_multiple_702-164-18", "result": "<TOOLCALL>Movies_3_FindMovies(directed_by=\"dontcare\", genre=\"dontcare\", cast=\"Katsunosuke Hori\")</TOOLCALL>", "input_token_count": 972, "output_token_count": 37, "latency": 7.26090145111084}
{"id": "live_multiple_709-164-25", "result": "<TOOLCALL>Movies_3_FindMovies(directed_by=\"Kirill Mikhanovsky\", genre=\"Comedy-drama\")</TOOLCALL>", "input_token_count": 979, "output_token_count": 33, "latency": 6.875065565109253}
{"id": "live_multiple_718-165-5", "result": "<TOOLCALL>[Hotels_2_BookHouse(where_to=\"Austin, TX\", number_of_adults=4, check_in_date=\"05/12/2023\", check_out_date=\"05/18/2023\")]</TOOLCALL>", "input_token_count": 1148, "output_token_count": 63, "latency": 9.175900220870972}
{"id": "live_multiple_734-167-5", "result": "<TOOLCALL>Homes_2_FindHomeByArea(area=\"Los Angeles, CA\", intent=\"buy\", number_of_beds=2, number_of_baths=2, has_garage=True)</TOOLCALL>", "input_token_count": 1156, "output_token_count": 48, "latency": 8.43208932876587}
{"id": "live_multiple_759-169-14", "result": "<TOOLCALL>Media_3_FindMovies(genre=\"Comedy\")</TOOLCALL>", "input_token_count": 1540, "output_token_count": 22, "latency": 6.251961708068848}
{"id": "live_multiple_799-175-5", "result": "<TOOLCALL>Weather_1_GetWeather(city=\"Lagunitas, CA\", date=\"2023-04-15\")</TOOLCALL>", "input_token_count": 1653, "output_token_count": 38, "latency": 7.492918491363525}
{"id": "live_multiple_800-175-6", "result": "<TOOLCALL>Weather_1_GetWeather(city=\"San Pablo, CA\", date=\"2023-04-10\")</TOOLCALL>", "input_token_count": 1655, "output_token_count": 36, "latency": 7.400701284408569}
{"id": "live_multiple_808-175-14", "result": "<TOOLCALL>Weather_1_GetWeather(city=\"Antioch, CA\", date=\"2023-10-01\")</TOOLCALL>", "input_token_count": 1654, "output_token_count": 37, "latency": 7.483160495758057}
{"id": "live_multiple_813-176-4", "result": "<TOOLCALL>Alarm_1_AddAlarm(new_alarm_time=\"16:30\", new_alarm_name=\"Leave for home\")</TOOLCALL>", "input_token_count": 560, "output_token_count": 34, "latency": 7.222460031509399}
{"id": "live_multiple_840-178-15", "result": "<TOOLCALL>Music_3_LookupMusic(artist=\"Hillbilly\", album=\"Gotta Be Me\", genre=\"Country\", year=\"2019\")</TOOLCALL>\n<TOOLCALL>Music_3_PlayMedia(track=\"style\", artist=\"Hillbilly\", album=\"Gotta Be Me\", device=\"Living room\")</TOOLCALL>", "input_token_count": 1028, "output_token_count": 81, "latency": 9.722559213638306}
{"id": "live_multiple_847-179-1", "result": "<TOOLCALL>[Restaurants_2_ReserveRestaurant(restaurant_name=\"Balthazar\", location=\"New York, NY\", time=\"20:00\", number_of_seats=4, date=\"2023-10-13\")}</TOOLCALL>", "input_token_count": 937, "output_token_count": 61, "latency": 9.148841142654419}
{"id": "live_multiple_855-180-3", "result": "<TOOLCALL>Buses_3_FindBus(from_city=\"Fresno, CA\", to_city=\"Los Angeles, CA\", departure_date=\"03/10/2023\", num_passengers=1)</TOOLCALL>", "input_token_count": 1459, "output_token_count": 52, "latency": 8.92580270767212}
{"id": "live_multiple_881-183-6", "result": "<TOOLCALL>Travel_1_FindAttractions(location=\"San Francisco, CA\", free_entry=\"True\", good_for_kids=\"True\", category=\"dontcare\")</TOOLCALL>", "input_token_count": 1841, "output_token_count": 41, "latency": 8.1907799243927}
{"id": "live_multiple_893-185-3", "result": "<TOOLCALL>Payment_1_MakePayment(payment_method=\"debit card\", amount=90.0, receiver=\"Alice\")</TOOLCALL>", "input_token_count": 1316, "output_token_count": 34, "latency": 7.270261764526367}
{"id": "live_multiple_905-186-2", "result": "<TOOLCALL>Trains_1_GetTrainTickets(_from=\"Portland, OR\", to=\"Seattle, WA\", date_of_journey=\"2023-05-14\", journey_start_time=\"23:59\", number_of_adults=4, trip_protection=True, _class=\"Business\")</TOOLCALL>", "input_token_count": 1460, "output_token_count": 75, "latency": 9.595191717147827}
{"id": "live_multiple_911-190-0", "result": "<TOOLCALL>view_service_provider_profile(service_id=1)</TOOLCALL>", "input_token_count": 1101, "output_token_count": 19, "latency": 6.318483829498291}
{"id": "live_multiple_934-191-22", "result": "<TOOLCALL>get_service_providers(province_id=1, district_name=\"Chatuchak\", start_available_date=\"2024-03-22 00:00:00\", end_available_date=\"2024-03-22 23:59:59\", avg_rating=4.0)</TOOLCALL>", "input_token_count": 1352, "output_token_count": 82, "latency": 9.849416732788086}
{"id": "live_multiple_953-201-1", "result": "<TOOLCALL>flight.status.check(flight_identifier=\"IND5463\", passenger_name=\"karan\", ticket_number=\"IND5463\")</TOOLCALL>", "input_token_count": 672, "output_token_count": 39, "latency": 8.07530951499939}
{"id": "live_multiple_973-213-0", "result": "<TOOLCALL>get_service_providers(province_id=1, service_ids=[2])</TOOLCALL>", "input_token_count": 1230, "output_token_count": 26, "latency": 6.874849796295166}
{"id": "live_multiple_985-216-0", "result": "<TOOLCALL>reminders_complete(token=\"1231289312\")</TOOLCALL>", "input_token_count": 5768, "output_token_count": 27, "latency": 7.346520662307739}
{"id": "live_multiple_989-220-0", "result": "<TOOLCALL>get_websites(status_filter=\"active\", include_metadata=False)</TOOLCALL>", "input_token_count": 641, "output_token_count": 22, "latency": 6.6323442459106445}
{"id": "live_multiple_996-227-0", "result": "<TOOLCALL>add_service_config(service_name=\"fdsa\", configurations={\"timeout\": 30, \"retry_count\": 5, \"endpoint\": \"https://api.fdsa-service.com\", \"auth_required\": true})</TOOLCALL>", "input_token_count": 894, "output_token_count": 53, "latency": 8.98308253288269}
{"id": "live_multiple_997-228-0", "result": "<TOOLCALL>usage_api.UsageApi.get_hosts_per_day(day=15, month=2, year=2022)</TOOLCALL>", "input_token_count": 797, "output_token_count": 34, "latency": 7.72727632522583}
{"id": "live_multiple_1002-232-1", "result": "<TOOLCALL>api_token_api.APITokenApi.get_api_tokens(user_id=\"user123\", include_expired=False)</TOOLCALL>", "input_token_count": 752, "output_token_count": 32, "latency": 7.551506280899048}
{"id": "live_multiple_1016-245-0", "result": "<TOOLCALL>create_global_application_alert_config(name=\"UrgentAlert77f7\", alert_type=\"error_rate\", threshold=0.05, recipients=['admin@example.com', 'support@example.com'])</TOOLCALL>", "input_token_count": 848, "output_token_count": 51, "latency": 9.033114194869995}
{"id": "live_multiple_1017-246-0", "result": "<TOOLCALL>[events_api.EventsApi.get_event(eventId=\"efJG9\")]</TOOLCALL>", "input_token_count": 513, "output_token_count": 25, "latency": 6.85898232460022}
{"id": "live_multiple_1027-255-1", "result": "<TOOLCALL>CustomDashboardsApi.get_shareable_api_tokens(user_id=\"12345\", include_revoked=False)</TOOLCALL>\n<TOOLCALL>api_token_api.APITokenApi.get_api_tokens(include_expired=False, page=1, page_size=100)</TOOLCALL>", "input_token_count": 803, "output_token_count": 67, "latency": 9.52751636505127}
{"id": "live_multiple_1040-267-0", "result": "<TOOLCALL>detail_experience_and_education(experience_or_education_type=\"Education at Universitas Sebelas Maret (UNS)\", experience_or_education_name=\"Universitas Sebelas Maret (UNS)\")</TOOLCALL>", "input_token_count": 1478, "output_token_count": 51, "latency": 9.02290654182434}
{"id": "live_multiple_1051-278-0", "result": "<TOOLCALL>set_alarm(alarm_time=\"2023-12-01 07:00\", purpose=\"wake up for meeting\")</TOOLCALL>", "input_token_count": 780, "output_token_count": 41, "latency": 8.524140357971191}
